ncephes/_testit.py
ncephes/__init__.py
ncephes/_ffi.so
ncephes/interface.h
ncephes/.libs/libhcephes-4b6a1436.so.0.3.3
ncephes/test/test_ellf.py
ncephes/test/__init__.py
ncephes/test/test_numba.py
ncephes/test/test_cprob.py
ncephes/test/test_misc.py
ncephes/test/test_bessel.py
ncephes-1.1.0.dist-info/WHEEL
ncephes-1.1.0.dist-info/top_level.txt
ncephes-1.1.0.dist-info/METADATA
ncephes-1.1.0.dist-info/RECORD
