Metadata-Version: 2.1
Name: ncephes
Version: 1.1.0
Summary: Python interface for the Cephes library
Home-page: https://github.com/limix/ncephes
Author: Danilo Horta
Author-email: horta@ebi.ac.uk
Maintainer: Danilo Horta
Maintainer-email: horta@ebi.ac.uk
License: MIT
Download-URL: https://github.com/limix/ncephes
Keywords: cephes,netlib,math,numba
Platform: Windows
Platform: MacOS
Platform: Linux
Classifier: Development Status :: 5 - Production/Stable
Classifier: Environment :: Console
Classifier: License :: OSI Approved :: MIT License
Classifier: Operating System :: OS Independent
Classifier: Programming Language :: Python
Requires-Dist: cffi (>=1.11.5)
Requires-Dist: numpy (>=1.13.0)
Requires-Dist: pytest (>=3.6.3)
